feds/__init__.py
feds/client.py
feds/exceptions.py
feds/fetch.py
feds.py-1.2.dist-info/LICENSE
feds.py-1.2.dist-info/METADATA
feds.py-1.2.dist-info/WHEEL
feds.py-1.2.dist-info/top_level.txt
feds.py-1.2.dist-info/RECORD
