Metadata-Version: 2.1
Name: feds.py
Version: 1.2
Summary: A feds.lol API wrapper for Python.
Home-page: https://github.com/addi00000/feds.py
Author: addi00000
Author-email: addidix@proton.me
License: AGPL-3.0
Classifier: Programming Language :: Python :: 3
Classifier: License :: OSI Approved :: GNU Affero General Public License v3
Classifier: Operating System :: OS Independent
Requires-Python: >=3.6
License-File: LICENSE
Requires-Dist: requests
Requires-Dist: bs4
